awattar/__init__.py
awattar/cli.py
awattar/client.py
awattar/marketitem.py
examples/__init__.py
examples/async_example.py
examples/example.py
awattar-0.8.1.dist-info/LICENSE
awattar-0.8.1.dist-info/METADATA
awattar-0.8.1.dist-info/WHEEL
awattar-0.8.1.dist-info/entry_points.txt
awattar-0.8.1.dist-info/top_level.txt
awattar-0.8.1.dist-info/RECORD
