Metadata-Version: 2.1
Name: awattar
Version: 0.8.1
Summary: aWATTar Client to analyse the energy market data
Author-email: Peter Gransdorfer <peter.gransdorfer@cattronix.com>
License: GPL-3.0
Project-URL: Homepage, https://github.com/Gransi/awattar
Project-URL: Download, https://github.com/Gransi/awattar
Project-URL: Tracker, https://github.com/Gransi/awattar/issues
Project-URL: Source, https://github.com/Gransi/awattar
Keywords: awattar,energy market price api
Classifier: Development Status :: 4 - Beta
Classifier: Programming Language :: Python :: 3
Classifier: License :: OSI Approved :: GNU General Public License (GPL)
Classifier: Operating System :: OS Independent
Classifier: Programming Language :: Python :: 3.9
Classifier: Programming Language :: Python :: 3.10
Classifier: Programming Language :: Python :: 3.11
Classifier: Topic :: Software Development :: Libraries
Classifier: Topic :: Software Development :: Libraries :: Python Modules
Requires-Python: >=3.8
License-File: LICENSE
Requires-Dist: requests >=2.31.0
Requires-Dist: datetime
Requires-Dist: python-dateutil
Requires-Dist: click >=8.1.7
Requires-Dist: aiohttp
Requires-Dist: async-timeout
Requires-Dist: tzlocal
Provides-Extra: dev
Requires-Dist: ruff >=0.1.5 ; extra == 'dev'
Provides-Extra: test
Requires-Dist: ruff >=0.1.5 ; extra == 'test'
Requires-Dist: types-requests ; extra == 'test'
Requires-Dist: types-python-dateutil ; extra == 'test'
Requires-Dist: pytest >=7.1.3 ; extra == 'test'
Requires-Dist: pytest-ruff >=0.2.1 ; extra == 'test'
Requires-Dist: pytest-mypy >=0.10.3 ; extra == 'test'
